SPImaster.v
// SPI Master
module spi_master( 
    // Control Signals
    input clk,
    input en,
    output reg ack,
    // Data signals
    input [7:0] data_in,
    output [7:0] data_out,
    // SPI Interface signals
    output sck,
    output cs,
    output mosi,
    input miso
);
    // sck signal generation (using divide by 8 clock divider)
    reg [3:0] divider;
    always@(posedge clk or negedge en)begin
        if(!en)
        divider <= 0;
        else
        divider <= divider+1;
    end
    assign sck = divider[3];
    
    // cs signal 
    assign cs = en;

    // Logic for detecting rising and falling edges of SCK signal.
    reg [2:0]sckr;
    always@(posedge clk)
      sckr <= {sckr[1:0],sck};
    wire sck_rising_edge = (!sckr[2]) & sckr[1];
    wire sck_falling_edge = sckr[2] & (!sckr[1]);

    // en signal
    reg [2:0]enr;
    always@(posedge clk)
      enr <= {enr[1:0],en};
    assign en_rising_edge = (!enr[2]) & enr[1];
    assign en_falling_edge = enr[2] & (!enr[1]); 
    assign en_active = enr[1];

    // Synchronizing MISO data to SCK clock
    reg [1:0] MISOr;  
    always @(posedge clk) 
      MISOr <= {MISOr[0], miso};
    wire MISO_data = MISOr[1];

    // Receiving data (MSB first)
    reg [2:0]bit_cnt; // 3 bit counter
    reg [7:0] r_byte; // received byte
    
    always@(posedge clk)
        begin
            if(!en)
                bit_cnt <= 3'b000;
            else
                if(sck_rising_edge)
                    begin
                        bit_cnt <= bit_cnt + 3'b001;
                        r_byte <= {r_byte[6:0],MISO_data};
                    end
        end

    always@(posedge clk)
        ack <= (en)&&(sck_rising_edge)&&(bit_cnt == 3'b111);

// if ack bit is high, output the data recieved.
// ack bit is goes high only for one clock cycle, in that clk cycle, the received data must be output.
    assign data_out = ack? r_byte: (8'bz);
    
    // Sending Data
    reg [7:0] s_data;
    always@(posedge clk)
    begin
        if(en)
        begin
        if(en_rising_edge)
            s_data<=data_in;
        
        if(sck_falling_edge)
        begin
            if(bit_cnt == 0)
            s_data<=data_in;
            else
            s_data<={s_data[6:0], s_data[7]};
        end

        end
    end

    assign mosi = (en)?s_data[7]:1'bz;
    
endmodule

SPImaster_tb.v
`timescale 1ns/1ps 
module SPI_master_tb;
    // Control signals
    reg clk;
    reg en;
    wire ack;
    // Data signals
    wire [7:0] data_recevied;
    reg [7:0] data_sent;
    // SPI inteface signals
    wire sck;
    wire mosi;
    reg miso;
    wire cs;

    // Instantiation
    spi_master master(clk, en, ack, data_sent, data_recevied, sck, cs, mosi, miso);

    // Signal initiation and monitoring
      initial
    begin
      $dumpfile("results_m.vcd");
      $dumpvars;
      clk = 1'b0;
      en = 1'b0;
      data_sent = 8'b1011_1001;
      miso = 1'b1;
    end

    initial
        forever
            #1 clk <= ~clk;
    
    initial
        #12.5 en <= 1'b1;

    initial
        #100 miso <= 1'b0;

    initial
        #500 $finish;

endmodule

results_m.vcd
$date
	Mon Sep 16 13:06:03 2024
$end
$version
	Icarus Verilog
$end
$timescale
	1ps
$end
$scope module SPI_master_tb $end
$var wire 1 ! sck $end
$var wire 1 " mosi $end
$var wire 8 # data_recevied [7:0] $end
$var wire 1 $ cs $end
$var wire 1 % ack $end
$var reg 1 & clk $end
$var reg 8 ' data_sent [7:0] $end
$var reg 1 ( en $end
$var reg 1 ) miso $end
$scope module master $end
$var wire 1 & clk $end
$var wire 1 $ cs $end
$var wire 8 * data_in [7:0] $end
$var wire 1 ( en $end
$var wire 1 + en_falling_edge $end
$var wire 1 , en_rising_edge $end
$var wire 1 ) miso $end
$var wire 1 - sck_falling_edge $end
$var wire 1 . sck_rising_edge $end
$var wire 1 ! sck $end
$var wire 1 " mosi $end
$var wire 1 / en_active $end
$var wire 8 0 data_out [7:0] $end
$var wire 1 1 MISO_data $end
$var reg 2 2 MISOr [1:0] $end
$var reg 1 % ack $end
$var reg 3 3 bit_cnt [2:0] $end
$var reg 4 4 divider [3:0] $end
$var reg 3 5 enr [2:0] $end
$var reg 8 6 r_byte [7:0] $end
$var reg 8 7 s_data [7:0] $end
$var reg 3 8 sckr [2:0] $end
$upscope $end
$upscope $end
$enddefinitions $end
#0
$dumpvars
bx 8
bx 7
bx 6
bx 5
b0 4
bx 3
bx 2
x1
bx 0
x/
x.
x-
x,
x+
b10111001 *
1)
0(
b10111001 '
0&
x%
0$
bx #
z"
0!
$end
#1000
bz #
bz 0
bx0 8
bx0 5
bx1 2
b0 3
0%
1&
#2000
0&
#3000
0,
0.
11
0/
b11 2
bx00 5
bx00 8
1&
#4000
0&
#5000
0-
0+
b0 8
b0 5
1&
#6000
0&
#7000
1&
#8000
0&
#9000
1&
#10000
0&
#11000
1&
#12000
0&
#12500
x"
1$
1(
#13000
b1 5
b1 4
1&
#14000
0&
#15000
1,
1/
b11 5
b10 4
1&
#16000
0&
#17000
0,
1"
b111 5
b10111001 7
b11 4
1&
#18000
0&
#19000
b100 4
1&
#20000
0&
#21000
b101 4
1&
#22000
0&
#23000
b110 4
1&
#24000
0&
#25000
b111 4
1&
#26000
0&
#27000
1!
b1000 4
1&
#28000
0&
#29000
b1 8
b1001 4
1&
#30000
0&
#31000
1.
b11 8
b1010 4
1&
#32000
0&
#33000
0.
b111 8
bx1 6
b1 3
b1011 4
1&
#34000
0&
#35000
b1100 4
1&
#36000
0&
#37000
b1101 4
1&
#38000
0&
#39000
b1110 4
1&
#40000
0&
#41000
b1111 4
1&
#42000
0&
#43000
0!
b0 4
1&
#44000
0&
#45000
b110 8
b1 4
1&
#46000
0&
#47000
1-
b100 8
b10 4
1&
#48000
0&
#49000
0-
0"
b0 8
b1110011 7
b11 4
1&
#50000
0&
#51000
b100 4
1&
#52000
0&
#53000
b101 4
1&
#54000
0&
#55000
b110 4
1&
#56000
0&
#57000
b111 4
1&
#58000
0&
#59000
1!
b1000 4
1&
#60000
0&
#61000
b1 8
b1001 4
1&
#62000
0&
#63000
1.
b11 8
b1010 4
1&
#64000
0&
#65000
0.
b111 8
bx11 6
b10 3
b1011 4
1&
#66000
0&
#67000
b1100 4
1&
#68000
0&
#69000
b1101 4
1&
#70000
0&
#71000
b1110 4
1&
#72000
0&
#73000
b1111 4
1&
#74000
0&
#75000
0!
b0 4
1&
#76000
0&
#77000
b110 8
b1 4
1&
#78000
0&
#79000
1-
b100 8
b10 4
1&
#80000
0&
#81000
0-
1"
b0 8
b11100110 7
b11 4
1&
#82000
0&
#83000
b100 4
1&
#84000
0&
#85000
b101 4
1&
#86000
0&
#87000
b110 4
1&
#88000
0&
#89000
b111 4
1&
#90000
0&
#91000
1!
b1000 4
1&
#92000
0&
#93000
b1 8
b1001 4
1&
#94000
0&
#95000
1.
b11 8
b1010 4
1&
#96000
0&
#97000
0.
b111 8
bx111 6
b11 3
b1011 4
1&
#98000
0&
#99000
b1100 4
1&
#100000
0&
0)
#101000
b10 2
b1101 4
1&
#102000
0&
#103000
01
b0 2
b1110 4
1&
#104000
0&
#105000
b1111 4
1&
#106000
0&
#107000
0!
b0 4
1&
#108000
0&
#109000
b110 8
b1 4
1&
#110000
0&
#111000
1-
b100 8
b10 4
1&
#112000
0&
#113000
0-
b0 8
b11001101 7
b11 4
1&
#114000
0&
#115000
b100 4
1&
#116000
0&
#117000
b101 4
1&
#118000
0&
#119000
b110 4
1&
#120000
0&
#121000
b111 4
1&
#122000
0&
#123000
1!
b1000 4
1&
#124000
0&
#125000
b1 8
b1001 4
1&
#126000
0&
#127000
1.
b11 8
b1010 4
1&
#128000
0&
#129000
0.
b111 8
bx1110 6
b100 3
b1011 4
1&
#130000
0&
#131000
b1100 4
1&
#132000
0&
#133000
b1101 4
1&
#134000
0&
#135000
b1110 4
1&
#136000
0&
#137000
b1111 4
1&
#138000
0&
#139000
0!
b0 4
1&
#140000
0&
#141000
b110 8
b1 4
1&
#142000
0&
#143000
1-
b100 8
b10 4
1&
#144000
0&
#145000
0-
b0 8
b10011011 7
b11 4
1&
#146000
0&
#147000
b100 4
1&
#148000
0&
#149000
b101 4
1&
#150000
0&
#151000
b110 4
1&
#152000
0&
#153000
b111 4
1&
#154000
0&
#155000
1!
b1000 4
1&
#156000
0&
#157000
b1 8
b1001 4
1&
#158000
0&
#159000
1.
b11 8
b1010 4
1&
#160000
0&
#161000
0.
b111 8
bx11100 6
b101 3
b1011 4
1&
#162000
0&
#163000
b1100 4
1&
#164000
0&
#165000
b1101 4
1&
#166000
0&
#167000
b1110 4
1&
#168000
0&
#169000
b1111 4
1&
#170000
0&
#171000
0!
b0 4
1&
#172000
0&
#173000
b110 8
b1 4
1&
#174000
0&
#175000
1-
b100 8
b10 4
1&
#176000
0&
#177000
0-
0"
b0 8
b110111 7
b11 4
1&
#178000
0&
#179000
b100 4
1&
#180000
0&
#181000
b101 4
1&
#182000
0&
#183000
b110 4
1&
#184000
0&
#185000
b111 4
1&
#186000
0&
#187000
1!
b1000 4
1&
#188000
0&
#189000
b1 8
b1001 4
1&
#190000
0&
#191000
1.
b11 8
b1010 4
1&
#192000
0&
#193000
0.
b111 8
bx111000 6
b110 3
b1011 4
1&
#194000
0&
#195000
b1100 4
1&
#196000
0&
#197000
b1101 4
1&
#198000
0&
#199000
b1110 4
1&
#200000
0&
#201000
b1111 4
1&
#202000
0&
#203000
0!
b0 4
1&
#204000
0&
#205000
b110 8
b1 4
1&
#206000
0&
#207000
1-
b100 8
b10 4
1&
#208000
0&
#209000
0-
b0 8
b1101110 7
b11 4
1&
#210000
0&
#211000
b100 4
1&
#212000
0&
#213000
b101 4
1&
#214000
0&
#215000
b110 4
1&
#216000
0&
#217000
b111 4
1&
#218000
0&
#219000
1!
b1000 4
1&
#220000
0&
#221000
b1 8
b1001 4
1&
#222000
0&
#223000
1.
b11 8
b1010 4
1&
#224000
0&
#225000
0.
b111 8
bx1110000 6
b111 3
b1011 4
1&
#226000
0&
#227000
b1100 4
1&
#228000
0&
#229000
b1101 4
1&
#230000
0&
#231000
b1110 4
1&
#232000
0&
#233000
b1111 4
1&
#234000
0&
#235000
0!
b0 4
1&
#236000
0&
#237000
b110 8
b1 4
1&
#238000
0&
#239000
1-
b100 8
b10 4
1&
#240000
0&
#241000
0-
1"
b0 8
b11011100 7
b11 4
1&
#242000
0&
#243000
b100 4
1&
#244000
0&
#245000
b101 4
1&
#246000
0&
#247000
b110 4
1&
#248000
0&
#249000
b111 4
1&
#250000
0&
#251000
1!
b1000 4
1&
#252000
0&
#253000
b1 8
b1001 4
1&
#254000
0&
#255000
1.
b11 8
b1010 4
1&
#256000
0&
#257000
0.
b11100000 #
b11100000 0
b111 8
b11100000 6
b0 3
1%
b1011 4
1&
#258000
0&
#259000
bz #
bz 0
0%
b1100 4
1&
#260000
0&
#261000
b1101 4
1&
#262000
0&
#263000
b1110 4
1&
#264000
0&
#265000
b1111 4
1&
#266000
0&
#267000
0!
b0 4
1&
#268000
0&
#269000
b110 8
b1 4
1&
#270000
0&
#271000
1-
b100 8
b10 4
1&
#272000
0&
#273000
0-
b0 8
b10111001 7
b11 4
1&
#274000
0&
#275000
b100 4
1&
#276000
0&
#277000
b101 4
1&
#278000
0&
#279000
b110 4
1&
#280000
0&
#281000
b111 4
1&
#282000
0&
#283000
1!
b1000 4
1&
#284000
0&
#285000
b1 8
b1001 4
1&
#286000
0&
#287000
1.
b11 8
b1010 4
1&
#288000
0&
#289000
0.
b111 8
b11000000 6
b1 3
b1011 4
1&
#290000
0&
#291000
b1100 4
1&
#292000
0&
#293000
b1101 4
1&
#294000
0&
#295000
b1110 4
1&
#296000
0&
#297000
b1111 4
1&
#298000
0&
#299000
0!
b0 4
1&
#300000
0&
#301000
b110 8
b1 4
1&
#302000
0&
#303000
1-
b100 8
b10 4
1&
#304000
0&
#305000
0-
0"
b0 8
b1110011 7
b11 4
1&
#306000
0&
#307000
b100 4
1&
#308000
0&
#309000
b101 4
1&
#310000
0&
#311000
b110 4
1&
#312000
0&
#313000
b111 4
1&
#314000
0&
#315000
1!
b1000 4
1&
#316000
0&
#317000
b1 8
b1001 4
1&
#318000
0&
#319000
1.
b11 8
b1010 4
1&
#320000
0&
#321000
0.
b111 8
b10000000 6
b10 3
b1011 4
1&
#322000
0&
#323000
b1100 4
1&
#324000
0&
#325000
b1101 4
1&
#326000
0&
#327000
b1110 4
1&
#328000
0&
#329000
b1111 4
1&
#330000
0&
#331000
0!
b0 4
1&
#332000
0&
#333000
b110 8
b1 4
1&
#334000
0&
#335000
1-
b100 8
b10 4
1&
#336000
0&
#337000
0-
1"
b0 8
b11100110 7
b11 4
1&
#338000
0&
#339000
b100 4
1&
#340000
0&
#341000
b101 4
1&
#342000
0&
#343000
b110 4
1&
#344000
0&
#345000
b111 4
1&
#346000
0&
#347000
1!
b1000 4
1&
#348000
0&
#349000
b1 8
b1001 4
1&
#350000
0&
#351000
1.
b11 8
b1010 4
1&
#352000
0&
#353000
0.
b111 8
b0 6
b11 3
b1011 4
1&
#354000
0&
#355000
b1100 4
1&
#356000
0&
#357000
b1101 4
1&
#358000
0&
#359000
b1110 4
1&
#360000
0&
#361000
b1111 4
1&
#362000
0&
#363000
0!
b0 4
1&
#364000
0&
#365000
b110 8
b1 4
1&
#366000
0&
#367000
1-
b100 8
b10 4
1&
#368000
0&
#369000
0-
b0 8
b11001101 7
b11 4
1&
#370000
0&
#371000
b100 4
1&
#372000
0&
#373000
b101 4
1&
#374000
0&
#375000
b110 4
1&
#376000
0&
#377000
b111 4
1&
#378000
0&
#379000
1!
b1000 4
1&
#380000
0&
#381000
b1 8
b1001 4
1&
#382000
0&
#383000
1.
b11 8
b1010 4
1&
#384000
0&
#385000
0.
b111 8
b100 3
b1011 4
1&
#386000
0&
#387000
b1100 4
1&
#388000
0&
#389000
b1101 4
1&
#390000
0&
#391000
b1110 4
1&
#392000
0&
#393000
b1111 4
1&
#394000
0&
#395000
0!
b0 4
1&
#396000
0&
#397000
b110 8
b1 4
1&
#398000
0&
#399000
1-
b100 8
b10 4
1&
#400000
0&
#401000
0-
b0 8
b10011011 7
b11 4
1&
#402000
0&
#403000
b100 4
1&
#404000
0&
#405000
b101 4
1&
#406000
0&
#407000
b110 4
1&
#408000
0&
#409000
b111 4
1&
#410000
0&
#411000
1!
b1000 4
1&
#412000
0&
#413000
b1 8
b1001 4
1&
#414000
0&
#415000
1.
b11 8
b1010 4
1&
#416000
0&
#417000
0.
b111 8
b101 3
b1011 4
1&
#418000
0&
#419000
b1100 4
1&
#420000
0&
#421000
b1101 4
1&
#422000
0&
#423000
b1110 4
1&
#424000
0&
#425000
b1111 4
1&
#426000
0&
#427000
0!
b0 4
1&
#428000
0&
#429000
b110 8
b1 4
1&
#430000
0&
#431000
1-
b100 8
b10 4
1&
#432000
0&
#433000
0-
0"
b0 8
b110111 7
b11 4
1&
#434000
0&
#435000
b100 4
1&
#436000
0&
#437000
b101 4
1&
#438000
0&
#439000
b110 4
1&
#440000
0&
#441000
b111 4
1&
#442000
0&
#443000
1!
b1000 4
1&
#444000
0&
#445000
b1 8
b1001 4
1&
#446000
0&
#447000
1.
b11 8
b1010 4
1&
#448000
0&
#449000
0.
b111 8
b110 3
b1011 4
1&
#450000
0&
#451000
b1100 4
1&
#452000
0&
#453000
b1101 4
1&
#454000
0&
#455000
b1110 4
1&
#456000
0&
#457000
b1111 4
1&
#458000
0&
#459000
0!
b0 4
1&
#460000
0&
#461000
b110 8
b1 4
1&
#462000
0&
#463000
1-
b100 8
b10 4
1&
#464000
0&
#465000
0-
b0 8
b1101110 7
b11 4
1&
#466000
0&
#467000
b100 4
1&
#468000
0&
#469000
b101 4
1&
#470000
0&
#471000
b110 4
1&
#472000
0&
#473000
b111 4
1&
#474000
0&
#475000
1!
b1000 4
1&
#476000
0&
#477000
b1 8
b1001 4
1&
#478000
0&
#479000
1.
b11 8
b1010 4
1&
#480000
0&
#481000
0.
b111 8
b111 3
b1011 4
1&
#482000
0&
#483000
b1100 4
1&
#484000
0&
#485000
b1101 4
1&
#486000
0&
#487000
b1110 4
1&
#488000
0&
#489000
b1111 4
1&
#490000
0&
#491000
0!
b0 4
1&
#492000
0&
#493000
b110 8
b1 4
1&
#494000
0&
#495000
1-
b100 8
b10 4
1&
#496000
0&
#497000
0-
1"
b0 8
b11011100 7
b11 4
1&
#498000
0&
#499000
b100 4
1&
