SPIslave.v
// SPI Slave
module spi_slave (
    input clk,

    input sck,
    input mosi,
    output miso,
    input cs,

    output [7:0] dr, 
    input [7:0] ds,
    output ack  
);

// Write a logic for detecting rising and falling edges of SCK
// I understood why we can't do this detection with a single ff, but why can't we do away with 2? and why use 3?

  reg [2:0]sckr;
    always@(posedge clk)
      sckr <= {sckr[1:0],sck};
    wire sck_rising_edge = (!sckr[2]) & sckr[1];
    wire sck_falling_edge = sckr[2] & (!sckr[1]);

//  Similarly for detecting rising and falling edges on cs

  reg [2:0]csr;
    always@(posedge clk)
      csr <= {csr[1:0],cs};
    wire cs_rising_edge = (!csr[2]) & csr[1];  // when this is asserted message stops
    wire cs_falling_edge = csr[2] & (!csr[1]); // when this is asserted message starts
    wire cs_active = ~csr[1];

// Synchronising mosi
    reg [1:0] MOSIr;  
    always @(posedge clk) 
      MOSIr <= {MOSIr[0], mosi};
    wire MOSI_data = MOSIr[1];

// Receiving data (MSB first)
    reg [2:0]bit_cnt; // 3 bit counter
    reg [7:0] r_byte; // received byte
    reg ack;
    
    always@(posedge clk)
        begin
            if(!cs_active)
                bit_cnt <= 3'b000;
            else
                if(sck_rising_edge)
                    begin
                        bit_cnt <= bit_cnt + 3'b001;
                        r_byte <= {r_byte[6:0],MOSI_data};
                    end
        end

    always@(posedge clk)
        ack <= (cs_active)&&(sck_rising_edge)&&(bit_cnt == 3'b111);

// if ack bit is high, output the data recieved.
// ack bit is goes high only for one clock cycle, in that clk cycle, the received data must be output.
    assign dr = ack? r_byte: (8'bz);
    
// Sending data
  reg [7:0]MISO_data;
    always@(posedge clk)
        if(cs_active)
            begin
                if(cs_falling_edge)
                    MISO_data <= ds;
                else
                begin
                    if(sck_falling_edge)
                        begin
                          if(bit_cnt == 3'b000)
                            MISO_data <= ds;
                          else
                          	MISO_data <= MISO_data<<1;
                        end
                end     
            end
    
    assign miso = cs_active? MISO_data[7]: 1'bz;

endmodule

SPIslave_tb.v
// Code your testbench here
// or browse Examples
`timescale 1ns/1ps 
module spi_slave_tb;
  reg clk;
  reg sck;
  reg mosi;
  reg cs;
  
  reg [7:0] ds;
  
  wire miso;
  wire [7:0]dr;
  wire ack;
  
  spi_slave s1(clk, sck, mosi, miso, cs, dr, ds, ack);
  
  initial
    begin
      $dumpfile("results_s.vcd");
      $dumpvars;
      clk = 1'b1;
      cs = 1'b1;
      sck = 1'b0;
      mosi = 1'b1;
      ds = 8'b10101010;
    end
  
  initial
  	forever #0.500 clk <= ~clk;
  
  initial 
    forever #10 sck <= ~sck;
  
  initial
    #5 cs = 1'b0;
  
  initial
    #90 mosi = 1'b0;
 
  initial #200 $finish;
  
  
endmodule

results_s.vcd
$date
	Mon Sep 16 13:06:16 2024
$end
$version
	Icarus Verilog
$end
$timescale
	1ps
$end
$scope module spi_slave_tb $end
$var wire 1 ! miso $end
$var wire 8 " dr [7:0] $end
$var wire 1 # ack $end
$var reg 1 $ clk $end
$var reg 1 % cs $end
$var reg 8 & ds [7:0] $end
$var reg 1 ' mosi $end
$var reg 1 ( sck $end
$scope module s1 $end
$var wire 1 $ clk $end
$var wire 1 % cs $end
$var wire 1 ) cs_active $end
$var wire 1 * cs_falling_edge $end
$var wire 1 + cs_rising_edge $end
$var wire 8 , ds [7:0] $end
$var wire 1 ' mosi $end
$var wire 1 ( sck $end
$var wire 1 - sck_falling_edge $end
$var wire 1 . sck_rising_edge $end
$var wire 1 ! miso $end
$var wire 8 / dr [7:0] $end
$var wire 1 0 MOSI_data $end
$var reg 8 1 MISO_data [7:0] $end
$var reg 2 2 MOSIr [1:0] $end
$var reg 1 # ack $end
$var reg 3 3 bit_cnt [2:0] $end
$var reg 3 4 csr [2:0] $end
$var reg 8 5 r_byte [7:0] $end
$var reg 3 6 sckr [2:0] $end
$upscope $end
$upscope $end
$enddefinitions $end
#0
$dumpvars
bx0 6
bx 5
bx1 4
bx 3
bx1 2
bx 1
x0
bx /
x.
x-
b10101010 ,
x+
x*
x)
0(
1'
b10101010 &
1%
1$
x#
bx "
x!
$end
#500
0$
#1000
z!
0*
0)
0.
10
b11 2
bx11 4
bx00 6
1$
#1500
0$
#2000
0-
0+
bz "
bz /
b0 6
b111 4
b0 3
0#
1$
#2500
0$
#3000
1$
#3500
0$
#4000
1$
#4500
0$
#5000
b110 4
1$
0%
#5500
0$
#6000
x!
1*
1)
b100 4
1$
#6500
0$
#7000
1!
0*
b10101010 1
b0 4
1$
#7500
0$
#8000
1$
#8500
0$
#9000
1$
#9500
0$
#10000
b1 6
1$
1(
#10500
0$
#11000
1.
b11 6
1$
#11500
0$
#12000
0.
b111 6
bx1 5
b1 3
1$
#12500
0$
#13000
1$
#13500
0$
#14000
1$
#14500
0$
#15000
1$
#15500
0$
#16000
1$
#16500
0$
#17000
1$
#17500
0$
#18000
1$
#18500
0$
#19000
1$
#19500
0$
#20000
b110 6
1$
0(
#20500
0$
#21000
1-
b100 6
1$
#21500
0$
#22000
0-
0!
b0 6
b1010100 1
1$
#22500
0$
#23000
1$
#23500
0$
#24000
1$
#24500
0$
#25000
1$
#25500
0$
#26000
1$
#26500
0$
#27000
1$
#27500
0$
#28000
1$
#28500
0$
#29000
1$
#29500
0$
#30000
b1 6
1$
1(
#30500
0$
#31000
1.
b11 6
1$
#31500
0$
#32000
0.
b111 6
bx11 5
b10 3
1$
#32500
0$
#33000
1$
#33500
0$
#34000
1$
#34500
0$
#35000
1$
#35500
0$
#36000
1$
#36500
0$
#37000
1$
#37500
0$
#38000
1$
#38500
0$
#39000
1$
#39500
0$
#40000
b110 6
1$
0(
#40500
0$
#41000
1-
b100 6
1$
#41500
0$
#42000
0-
1!
b0 6
b10101000 1
1$
#42500
0$
#43000
1$
#43500
0$
#44000
1$
#44500
0$
#45000
1$
#45500
0$
#46000
1$
#46500
0$
#47000
1$
#47500
0$
#48000
1$
#48500
0$
#49000
1$
#49500
0$
#50000
b1 6
1$
1(
#50500
0$
#51000
1.
b11 6
1$
#51500
0$
#52000
0.
b111 6
bx111 5
b11 3
1$
#52500
0$
#53000
1$
#53500
0$
#54000
1$
#54500
0$
#55000
1$
#55500
0$
#56000
1$
#56500
0$
#57000
1$
#57500
0$
#58000
1$
#58500
0$
#59000
1$
#59500
0$
#60000
b110 6
1$
0(
#60500
0$
#61000
1-
b100 6
1$
#61500
0$
#62000
0-
0!
b0 6
b1010000 1
1$
#62500
0$
#63000
1$
#63500
0$
#64000
1$
#64500
0$
#65000
1$
#65500
0$
#66000
1$
#66500
0$
#67000
1$
#67500
0$
#68000
1$
#68500
0$
#69000
1$
#69500
0$
#70000
b1 6
1$
1(
#70500
0$
#71000
1.
b11 6
1$
#71500
0$
#72000
0.
b111 6
bx1111 5
b100 3
1$
#72500
0$
#73000
1$
#73500
0$
#74000
1$
#74500
0$
#75000
1$
#75500
0$
#76000
1$
#76500
0$
#77000
1$
#77500
0$
#78000
1$
#78500
0$
#79000
1$
#79500
0$
#80000
b110 6
1$
0(
#80500
0$
#81000
1-
b100 6
1$
#81500
0$
#82000
0-
1!
b0 6
b10100000 1
1$
#82500
0$
#83000
1$
#83500
0$
#84000
1$
#84500
0$
#85000
1$
#85500
0$
#86000
1$
#86500
0$
#87000
1$
#87500
0$
#88000
1$
#88500
0$
#89000
1$
#89500
0$
#90000
b1 6
b10 2
1$
1(
0'
#90500
0$
#91000
1.
00
b0 2
b11 6
1$
#91500
0$
#92000
0.
b111 6
bx11110 5
b101 3
1$
#92500
0$
#93000
1$
#93500
0$
#94000
1$
#94500
0$
#95000
1$
#95500
0$
#96000
1$
#96500
0$
#97000
1$
#97500
0$
#98000
1$
#98500
0$
#99000
1$
#99500
0$
#100000
b110 6
1$
0(
#100500
0$
#101000
1-
b100 6
1$
#101500
0$
#102000
0-
0!
b0 6
b1000000 1
1$
#102500
0$
#103000
1$
#103500
0$
#104000
1$
#104500
0$
#105000
1$
#105500
0$
#106000
1$
#106500
0$
#107000
1$
#107500
0$
#108000
1$
#108500
0$
#109000
1$
#109500
0$
#110000
b1 6
1$
1(
#110500
0$
#111000
1.
b11 6
1$
#111500
0$
#112000
0.
b111 6
bx111100 5
b110 3
1$
#112500
0$
#113000
1$
#113500
0$
#114000
1$
#114500
0$
#115000
1$
#115500
0$
#116000
1$
#116500
0$
#117000
1$
#117500
0$
#118000
1$
#118500
0$
#119000
1$
#119500
0$
#120000
b110 6
1$
0(
#120500
0$
#121000
1-
b100 6
1$
#121500
0$
#122000
0-
1!
b0 6
b10000000 1
1$
#122500
0$
#123000
1$
#123500
0$
#124000
1$
#124500
0$
#125000
1$
#125500
0$
#126000
1$
#126500
0$
#127000
1$
#127500
0$
#128000
1$
#128500
0$
#129000
1$
#129500
0$
#130000
b1 6
1$
1(
#130500
0$
#131000
1.
b11 6
1$
#131500
0$
#132000
0.
b111 6
bx1111000 5
b111 3
1$
#132500
0$
#133000
1$
#133500
0$
#134000
1$
#134500
0$
#135000
1$
#135500
0$
#136000
1$
#136500
0$
#137000
1$
#137500
0$
#138000
1$
#138500
0$
#139000
1$
#139500
0$
#140000
b110 6
1$
0(
#140500
0$
#141000
1-
b100 6
1$
#141500
0$
#142000
0-
0!
b0 6
b0 1
1$
#142500
0$
#143000
1$
#143500
0$
#144000
1$
#144500
0$
#145000
1$
#145500
0$
#146000
1$
#146500
0$
#147000
1$
#147500
0$
#148000
1$
#148500
0$
#149000
1$
#149500
0$
#150000
b1 6
1$
1(
#150500
0$
#151000
1.
b11 6
1$
#151500
0$
#152000
0.
b11110000 "
b11110000 /
b111 6
b11110000 5
b0 3
1#
1$
#152500
0$
#153000
bz "
bz /
0#
1$
#153500
0$
#154000
1$
#154500
0$
#155000
1$
#155500
0$
#156000
1$
#156500
0$
#157000
1$
#157500
0$
#158000
1$
#158500
0$
#159000
1$
#159500
0$
#160000
b110 6
1$
0(
#160500
0$
#161000
1-
b100 6
1$
#161500
0$
#162000
0-
1!
b0 6
b10101010 1
1$
#162500
0$
#163000
1$
#163500
0$
#164000
1$
#164500
0$
#165000
1$
#165500
0$
#166000
1$
#166500
0$
#167000
1$
#167500
0$
#168000
1$
#168500
0$
#169000
1$
#169500
0$
#170000
b1 6
1$
1(
#170500
0$
#171000
1.
b11 6
1$
#171500
0$
#172000
0.
b111 6
b11100000 5
b1 3
1$
#172500
0$
#173000
1$
#173500
0$
#174000
1$
#174500
0$
#175000
1$
#175500
0$
#176000
1$
#176500
0$
#177000
1$
#177500
0$
#178000
1$
#178500
0$
#179000
1$
#179500
0$
#180000
b110 6
1$
0(
#180500
0$
#181000
1-
b100 6
1$
#181500
0$
#182000
0-
0!
b0 6
b1010100 1
1$
#182500
0$
#183000
1$
#183500
0$
#184000
1$
#184500
0$
#185000
1$
#185500
0$
#186000
1$
#186500
0$
#187000
1$
#187500
0$
#188000
1$
#188500
0$
#189000
1$
#189500
0$
#190000
b1 6
1$
1(
#190500
0$
#191000
1.
b11 6
1$
#191500
0$
#192000
0.
b111 6
b11000000 5
b10 3
1$
#192500
0$
#193000
1$
#193500
0$
#194000
1$
#194500
0$
#195000
1$
#195500
0$
#196000
1$
#196500
0$
#197000
1$
#197500
0$
#198000
1$
#198500
0$
#199000
1$
#199500
0$
#200000
b110 6
1$
0(
