rough_work/rough.v
module clk_divider_8(
    input clk, 
    output sck, 
    input en);
  
  reg [2:0]divider;

  always@(posedge clk or negedge en)begin
  if(!en)
    divider <= 0;
  else
    divider <= divider+1;
  end
  assign sck = divider[2];
endmodule

rough_work/rough_tb.v
module tb;
  reg clk;
  reg en;
  wire sck;
  
  clk_divider_8 c(clk, sck, en);
  
   always begin
        #5 clk <= ~clk;
   end
  
  initial
    #120 $finish;
  
  initial
    begin
    clk<= 0;
    en <= 0;
    #1
    en <= 1;
    end
  
  initial
    begin
      $dumpfile("results_rough.vcd");
      $dumpvars;
    end
endmodule

rough_work/results_rough.vcd
$date
	Sat Aug 17 00:27:42 2024
$end
$version
	Icarus Verilog
$end
$timescale
	1s
$end
$scope module tb $end
$var wire 1 ! sck $end
$var reg 1 " clk $end
$var reg 1 # en $end
$scope module c $end
$var wire 1 " clk $end
$var wire 1 # en $end
$var wire 1 ! sck $end
$var reg 3 $ divider [2:0] $end
$upscope $end
$upscope $end
$enddefinitions $end
#0
$dumpvars
b0 $
0#
0"
0!
$end
#1
1#
#5
b1 $
1"
#10
0"
#15
b10 $
1"
#20
0"
#25
b11 $
1"
#30
0"
#35
1!
b100 $
1"
#40
0"
#45
b101 $
1"
#50
0"
#55
b110 $
1"
#60
0"
#65
b111 $
1"
#70
0"
#75
0!
b0 $
1"
#80
0"
#85
b1 $
1"
#90
0"
#95
b10 $
1"
#100
0"
#105
b11 $
1"
#110
0"
#115
1!
b100 $
1"
